interactx/__init__.py
interactx/confirm.py
interactx/file_dialog.py
interactx/input_types.py
interactx/selection.py
bn_interactx-0.0.1.dist-info/METADATA
bn_interactx-0.0.1.dist-info/WHEEL
bn_interactx-0.0.1.dist-info/top_level.txt
bn_interactx-0.0.1.dist-info/RECORD
